deferred_result/__init__.py
deferred_result/deferred_result.py
deferred_result/py.typed
deferred_result-0.1.1.dist-info/LICENSE
deferred_result-0.1.1.dist-info/METADATA
deferred_result-0.1.1.dist-info/WHEEL
deferred_result-0.1.1.dist-info/top_level.txt
deferred_result-0.1.1.dist-info/RECORD
