Metadata-Version: 2.1
Name: deferred-result
Version: 0.1.1
Summary: Simple DeferredResult
Home-page: https://github.com/Novakov/py-deferred-result
Author: Maciej Nowak
License: UNKNOWN
Platform: UNKNOWN
Classifier: Programming Language :: Python :: 3
Classifier: License :: OSI Approved :: MIT License
Classifier: Operating System :: OS Independent
Classifier: Development Status :: 3 - Alpha
Classifier: Intended Audience :: Developers
Classifier: Topic :: Utilities
Requires-Python: >=3.7
